setup.py
imbored/__init__.py
imbored.egg-info/PKG-INFO
imbored.egg-info/SOURCES.txt
imbored.egg-info/dependency_links.txt
imbored.egg-info/top_level.txt