Metadata-Version: 2.1
Name: imbored
Version: 0.0.0
Summary: Image Board
Home-page: UNKNOWN
Author: Perzan
Author-email: PerzanDevelopment@gmail.com
License: UNKNOWN
Platform: UNKNOWN
